README.md
setup.cfg
setup.py
confyaml/__init__.py
confyaml/confyaml.py
confyaml.egg-info/PKG-INFO
confyaml.egg-info/SOURCES.txt
confyaml.egg-info/dependency_links.txt
confyaml.egg-info/requires.txt
confyaml.egg-info/top_level.txt