Metadata-Version: 2.1
Name: confyaml
Version: 0.1.4
Summary: Deals with configuration files in yaml
Home-page: https://github.com/lucascoelhof/confyaml
Author: Lucas Coelho
Author-email: hello@lucascoelho.net
License: MIT
Download-URL: https://github.com/lucascoelhof/confyaml/archive/v0.1.4.tar.gz
Keywords: configuration,yaml,config
Platform: UNKNOWN
Classifier: Development Status :: 3 - Alpha
Classifier: Intended Audience :: Developers
Classifier: Topic :: Utilities
Classifier: License :: OSI Approved :: MIT License
Classifier: Programming Language :: Python :: 3
Classifier: Programming Language :: Python :: 3.4
Classifier: Programming Language :: Python :: 3.5
Classifier: Programming Language :: Python :: 3.6
Classifier: Programming Language :: Python :: 3.7
Classifier: Programming Language :: Python :: 3.8
